Workbook

Sheet Instructions
A1: MS Excel Practical Exam
A2: Total Questions: 30
A3: Difficulty Level: Medium
A4: Syllabus: Formulas, Logical Functions, Lookups, INDEX-MATCH, Pivot Tables & Charts, Data Analysis
A5: Attempt all questions using appropriate Excel tools/functions.

Sheet Sales_Data
A1: Order_ID | B1: Region | C1: Salesperson | D1: Product | E1: Quantity | F1: Unit_Price | G1: Sales_Date | H1: Total_Sales | I1: Category
A2: 301 | B2: North | C2: Amit | D2: Laptop | E2: 2 | F2: 45000 | G2: 05-01-2025 | H2: =E2*F2 -> 90000
A3: 302 | B3: South | C3: Riya | D3: Mobile | E3: 5 | F3: 15000 | G3: 07-01-2025 | H3: =E3*F3 -> 75000
A4: 303 | B4: East | C4: Kunal | D4: Tablet | E4: 3 | F4: 18000 | G4: 10-01-2025 | H4: =E4*F4 -> 54000
A5: 304 | B5: West | C5: Neha | D5: Laptop | E5: 1 | F5: 45000 | G5: 12-01-2025 | H5: =E5*F5 -> 45000
A6: 305 | B6: North | C6: Amit | D6: Mobile | E6: 4 | F6: 15000 | G6: 15-01-2025 | H6: =E6*F6 -> 60000
A7: 306 | B7: South | C7: Riya | D7: Laptop | E7: 2 | F7: 45000 | G7: 18-01-2025 | H7: =E7*F7 -> 90000

Sheet Product_Master
A1: Product | B1: Category | C1: GST_%
A2: Laptop | B2: Electronics | C2: 18
A3: Mobile | B3: Electronics | C3: 12
A4: Tablet | B4: Electronics | C4: 12

Sheet Student_pivot

Sheet Student_Marks
A1: Student_ID | B1: Name | C1: Concat | D1: Maths | E1: Statistics | F1: Excel | G1: Attendance_% | H1: Average Marks | I1: Eligible
A2: 1 | B2: Rahul | C2: =_xlfn.CONCAT(A2," ",B2) -> 1 Rahul | D2: 78 | E2: 82 | F2: 85 | G2: 92 | H2: =AVERAGE(D2,E2,F2) -> 81.666667 | I2: =IF(H2>85,"Eligible","Not Eligible") -> Not Eligible | J2: Topper | M2: Student with above 90%
A3: 2 | B3: Sneha | C3: =_xlfn.CONCAT(A3," ",B3) -> 2 Sneha | D3: 88 | E3: 91 | F3: 90 | G3: 96 | H3: =AVERAGE(D3,E3,F3) -> 89.666667 | I3: =IF(H3>85,"Eligible","Not Eligible") -> Eligible | J3: =_xlfn.XLOOKUP(J4,H2:H6,B2:B6) -> Pooja | M3: =COUNTIF(G2:G6,">90") -> 3
A4: 3 | B4: Arjun | C4: =_xlfn.CONCAT(A4," ",B4) -> 3 Arjun | D4: 65 | E4: 70 | F4: 72 | G4: 85 | H4: =AVERAGE(D4,E4,F4) -> 69 | I4: =IF(H4>85,"Eligible","Not Eligible") -> Not Eligible | J4: =MAX(H2:H6) -> 91.666667
A5: 4 | B5: Pooja | C5: =_xlfn.CONCAT(A5," ",B5) -> 4 Pooja | D5: 92 | E5: 89 | F5: 94 | G5: 98 | H5: =AVERAGE(D5,E5,F5) -> 91.666667 | I5: =IF(H5>85,"Eligible","Not Eligible") -> Eligible
A6: 5 | B6: Vikas | C6: =_xlfn.CONCAT(A6," ",B6) -> 5 Vikas | D6: 55 | E6: 60 | F6: 58 | G6: 80 | H6: =AVERAGE(D6,E6,F6) -> 57.666667 | I6: =IF(H6>85,"Eligible","Not Eligible") -> Not Eligible | M6: Median of Statistics marks
M7: =MEDIAN(E2:E6) -> 82
M9: S.D of Excel Marks
M10: =_xlfn.STDEV.S(H2:H6) -> 14.411415
M13: Row Labels | N13: Sum of Excel
M14: Arjun | N14: 72
M15: Pooja | N15: 94
M16: Rahul | N16: 85
M17: Sneha | N17: 90
M18: Vikas | N18: 58
M19: Grand Total | N19: 399

Sheet Sales_2
A1: Order_ID | B1: Region | C1: Salesperson | D1: Product | E1: Quantity | F1: Classify | G1: Unit_Price | H1: Sales_Date | I1: Total_Sales | J1: GST | K1: Payable_Amount | L1: Month Name
A2: 301 | B2: North | C2: Amit | D2: Laptop | E2: 2 | F2: =IF(E2>3,"High","Low") -> Low | G2: 45000 | H2: 45662 | I2: =E2*G2 -> 90000 | J2: =VLOOKUP(D2,Product_Master!$A$2:$C$4,3,0) -> 18 | K2: =I2+(J2/100)*I2 -> 106200 | L2: =TEXT(SalesTable[[#This Row],[Sales_Date]],"mmmm") -> January
A3: 302 | B3: South | C3: Riya | D3: Mobile | E3: 5 | F3: =IF(E3>3,"High","Low") -> High | G3: 15000 | H3: 07-01-2025 | I3: =E3*G3 -> 75000 | J3: =VLOOKUP(D3,Product_Master!$A$2:$C$4,3,0) -> 12 | K3: =I3+(J3/100)*I3 -> 84000 | L3: =TEXT(SalesTable[[#This Row],[Sales_Date]],"mmmm") -> January
A4: 303 | B4: East | C4: Kunal | D4: Tablet | E4: 3 | F4: =IF(E4>3,"High","Low") -> Low | G4: 18000 | H4: 10-01-2025 | I4: =E4*G4 -> 54000 | J4: =VLOOKUP(D4,Product_Master!$A$2:$C$4,3,0) -> 12 | K4: =I4+(J4/100)*I4 -> 60480 | L4: =TEXT(SalesTable[[#This Row],[Sales_Date]],"mmmm") -> January | P4: 26_Counitif
A5: 304 | B5: West | C5: Neha | D5: Laptop | E5: 1 | F5: =IF(E5>3,"High","Low") -> Low | G5: 45000 | H5: 12-01-2025 | I5: =E5*G5 -> 45000 | J5: =VLOOKUP(D5,Product_Master!$A$2:$C$4,3,0) -> 18 | K5: =I5+(J5/100)*I5 -> 53100 | L5: =TEXT(SalesTable[[#This Row],[Sales_Date]],"mmmm") -> January | P5: =COUNTIFS(SalesTable[Product],"Laptop",SalesTable[Region],"North") -> 1 | S5: Highlight values> | V5: Extracting 2 charcters
A6: 305 | B6: North | C6: Amit | D6: Mobile | E6: 4 | F6: =IF(E6>3,"High","Low") -> High | G6: 15000 | H6: 15-01-2025 | I6: =E6*G6 -> 60000 | J6: =VLOOKUP(D6,Product_Master!$A$2:$C$4,3,0) -> 12 | K6: =I6+(J6/100)*I6 -> 67200 | L6: =TEXT(SalesTable[[#This Row],[Sales_Date]],"mmmm") -> January | S6: 60000 | V6: =LEFT(F6,2) -> Hi
A7: 306 | B7: South | C7: Riya | D7: Laptop | E7: 2 | F7: =IF(E7>3,"High","Low") -> Low | G7: 45000 | H7: 18-01-2025 | I7: =E7*G7 -> 90000 | J7: =VLOOKUP(D7,Product_Master!$A$2:$C$4,3,0) -> 18 | K7: =I7+(J7/100)*I7 -> 106200 | L7: =TEXT(SalesTable[[#This Row],[Sales_Date]],"mmmm") -> January
J8: 4_Grand Total | K8: =SUM(K2:K7) -> 477180
P10: 5_Total Orders | Q10: =COUNTA(A2:A7) -> 6
A12: Sort Table
A13: {=_xlfn._xlws.SORT(A2:K7,11,)} -> 304 | B13: West | C13: Neha | D13: Laptop | E13: 1 | F13: Low | G13: 45000 | H13: 12-01-2025 | I13: 45000 | J13: 18 | K13: 53100 | P13: 6_regional_sales | U13: Max Amount | V13: =MAX(K2:K7) -> 106200
A14: 303 | B14: East | C14: Kunal | D14: Tablet | E14: 3 | F14: Low | G14: 18000 | H14: 10-01-2025 | I14: 54000 | J14: 12 | K14: 60480 | P14: North | Q14: South | R14: East | S14: West | U14: Min Amount | V14: =MIN(K2:K7) -> 53100
A15: 305 | B15: North | C15: Amit | D15: Mobile | E15: 4 | F15: High | G15: 15000 | H15: 15-01-2025 | I15: 60000 | J15: 12 | K15: 67200 | P15: =SUMIF($B$2:$B$7,P14,$I$2:$I$7) -> 150000 | Q15: =SUMIF($B$2:$B$7,Q14,$I$2:$I$7) -> 165000 | R15: =SUMIF($B$2:$B$7,R14,$I$2:$I$7) -> 54000 | S15: =SUMIF($B$2:$B$7,S14,$I$2:$I$7) -> 45000
A16: 302 | B16: South | C16: Riya | D16: Mobile | E16: 5 | F16: High | G16: 15000 | H16: 07-01-2025 | I16: 75000 | J16: 12 | K16: 84000
A17: 301 | B17: North | C17: Amit | D17: Laptop | E17: 2 | F17: Low | G17: 45000 | H17: 45662 | I17: 90000 | J17: 18 | K17: 106200
A18: 306 | B18: South | C18: Riya | D18: Laptop | E18: 2 | F18: Low | G18: 45000 | H18: 18-01-2025 | I18: 90000 | J18: 18 | K18: 106200
N21: Product wise total Sales
N22: Row Labels | O22: Sum of Total_Sales
N23: Laptop | O23: 225000
N24: Mobile | O24: 135000
N25: Tablet | O25: 54000
N26: Grand Total | O26: 414000
N28: Region Wise Total Sales
N29: Row Labels | O29: Sum of Total_Sales
N30: East | O30: 54000
N31: North | O31: 150000
N32: South | O32: 165000
N33: West | O33: 45000
N34: Grand Total | O34: 414000
A39: Order_ID | B39: Region | C39: Salesperson | D39: Product | E39: Quantity | F39: Unit_Price | G39: Sales_Date | H39: Total_Sales | I39: Category
A40: 301 | B40: North | C40: Amit | D40: Laptop | E40: 2 | F40: 45000 | G40: 05-01-2025 | H40: =E40*F40 -> 90000
A41: 302 | B41: South | C41: Riya | D41: Mobile | E41: 5 | F41: 15000 | G41: 07-01-2025 | H41: =E41*F41 -> 75000
A42: 303 | B42: East | C42: Kunal | D42: Tablet | E42: 3 | F42: 18000 | G42: 10-01-2025 | H42: =E42*F42 -> 54000
A43: 304 | B43: West | C43: Neha | D43: Laptop | E43: 1 | F43: 45000 | G43: 12-01-2025 | H43: =E43*F43 -> 45000
A44: 305 | B44: North | C44: Amit | D44: Mobile | E44: 4 | F44: 15000 | G44: 15-01-2025 | H44: =E44*F44 -> 60000
A45: 306 | B45: South | C45: Riya | D45: Laptop | E45: 2 | F45: 45000 | G45: 18-01-2025 | H45: =E45*F45 -> 90000

Sheet Sales Pivot
A10: Quantity | B10: (Multiple Items)
A12: Row Labels | B12: Sum of Total_Sales
A13: Laptop | B13: 180000
A14: Mobile | B14: 135000
A15: Tablet | B15: 54000
A16: Grand Total | B16: 369000

Sheet Questions
A1: 1. Calculate Total Sales for each order (Quantity × Unit_Price). | J1: 2
A2: 2. Calculate GST Amount using VLOOKUP from Product_Master. | J2: 2
A3: 3. Find Final Amount payable (Total Sales + GST). | J3: 2
A4: 4. Find Grand Total of Final Amount. | J4: 2
A5: 5. Count total number of orders using COUNTA. | J5: 2
A6: 6. Find Region-wise total sales using SUMIF. | J6: 2
A7: 7. Use IF to classify Quantity as High (>3) or Low (<=3). | J7: 2
A8: 8. Find the maximum and minimum Final Amount. | J8: 2
A9: 9. Extract month name from Sales_Date. | J9: 2
A10: 10. Sort Sales_Data by Final Amount (Descending). | J10: 2
A11: 11. Use INDEX-MATCH to fetch Product Category. | J11: 2
A12: 12. Calculate average marks of each student. | J12: 2
... A30: 30. Protect the Student_Marks sheet. | J30: 2
J32: =SUM(J1:J30) -> 60
